netbuilder/NeuralNet.py
netbuilder/__init__.py
netbuilder/__version__.py
netbuilder/_param_keys.py
netbuilder/activations.py
netbuilder/file_operations.py
netbuilder/loss.py
netbuilder/examples/__init__.py
netbuilder/examples/image_number.py
netbuilder/examples/simple_sample.py
netbuilder/examples/test_script.py
netbuilder/examples/trainingShapes.py
netbuilder/tests/__init__.py
netbuilder/tests/training_random.py
netbuilder-0.2.3.dist-info/LICENSE
netbuilder-0.2.3.dist-info/METADATA
netbuilder-0.2.3.dist-info/WHEEL
netbuilder-0.2.3.dist-info/top_level.txt
netbuilder-0.2.3.dist-info/RECORD
