Metadata-Version: 2.1
Name: netbuilder
Version: 0.2.3
Summary: Allows to create and train fully connected feedforward deep neural networks in a simple way.
Home-page: https://github.com/andresberejnoi/NetBuilder
Author: Andres Berejnoi
Author-email: andresberejnoi@gmail.com
License: MIT
Download-URL: https://github.com/andresberejnoi/NetBuilder/archive/v0.2.3.tar.gz
Keywords: Neural Network,machine learning,AI,artificial intelligence,MLP
Platform: UNKNOWN
Classifier: Programming Language :: Python
Classifier: Programming Language :: Python :: 3
Classifier: Development Status :: 3 - Alpha
Classifier: Operating System :: Unix
Classifier: Intended Audience :: Education
Classifier: Intended Audience :: Developers
Classifier: Topic :: Scientific/Engineering :: Artificial Intelligence
Requires-Dist: numpy (>=1.12)
Requires-Dist: PyYAML (>=3.12)
